<adsxml>
<ads>
<pathURL>
https://raw.githubusercontent.com/CenterDevpiOS/img/master/GrupoMXXHDPI.png
</pathURL>
<adURL>http://codecanyon.net/user/kapova/portfolio</adURL>
</ads>
<ads>
<pathURL>
https://raw.githubusercontent.com/CenterDevpiOS/img/master/GrupoMXXHDPI.png
</pathURL>
<adURL>http://codecanyon.net/user/kapova/portfolio</adURL>
</ads>
<ads>
<pathURL>
https://raw.githubusercontent.com/CenterDevpiOS/img/master/GrupoMXXHDPI.png
</pathURL>
<adURL>http://codecanyon.net/user/kapova/portfolio</adURL>
</ads>
<ads>
<pathURL>
https://raw.githubusercontent.com/CenterDevpiOS/img/master/GrupoMXXHDPI.png
</pathURL>
<adURL>http://codecanyon.net/user/kapova/portfolio</adURL>
</ads>
<ads>
<pathURL>
https://raw.githubusercontent.com/CenterDevpiOS/img/master/GrupoMXXHDPI.png
</pathURL>
<adURL>http://codecanyon.net/user/kapova/portfolio</adURL>
</ads>
</adsxml>
